{
  "text": "Sotto il suo profilo pratico, un modo militante di creare a favore di una maggiore varietà di forme ibride e collettive, creazione sperimentale popolare, variazioni che mettono in discussione la norma. Probabilmente dietro Les Barques c'è un progetto morale da definire, che lo rende un'opera d'arte documentaria e non un'opera documentaria, ma il confine è sottile. Gli oggetti qui documentati non sono esempi di fatti sociali generali che possono essere studiati con un approccio statistico, ma gesti singolari che, alla luce dell'opera, sembrano attraversati dalla stessa ontologia, nella questione della mancanza. E una performatività (il gesto dell'archiviazione è già un gesto artistico, un'opera collettiva nel presente, nel momento stesso della registrazione) che non sembra intuitivamente poter essere associata all'archiviazione documentaria.",
  "image": "img_1995.jpg",
  "audio": "Hapsita thala - Durbali.mp3",
  "cycle": 1,
  "day": 1,
  "total_days": 30
}